<Data>
	<Samples>
		<i kind="db" path="/cdn/db/" name="employees.db"/>
		<i kind="db" path="/cdn/db/" name="sales.db"/>
		<i kind="sql" path="/cdn/db/" name="employees.sql"/>
	</Samples>

	<Sidebar>
		<!-- <i icon="server" name="Server 1" />
		<i icon="file" name="sales.db" state="expanded">
			<i icon="database" name="Database 1" state="expanded">
				<i icon="table" name="Table 1" />
				<i icon="table" name="Table 2" state="expanded">
					<i leaf="end" icon="column" name="id" />
					<i leaf="end" icon="column" name="name" />
					<i leaf="end" icon="column" name="city" />
					<i leaf="end" icon="column" name="department" />
					<i leaf="end" icon="column" name="salary" />
				</i>
				<i icon="table" name="Table 3" />
			</i>
			<i icon="database" name="Database 2" />
			<i icon="database" name="Database 3" />
		</i>
		<i icon="server" name="Server 3">
			<i icon="database" name="Database 2"/>
			<i icon="database" name="Database 3"/>
		</i>
		<i icon="server" name="Server 4" /> -->
	</Sidebar>

	<Result>
		<i id="11" name="Diane" city="London" department="hr" salary="70" />
		<i id="12" name="Bob" city="London" department="hr" salary="78" />
		<i id="21" name="Emma" city="London" department="it" salary="84" />
		<i id="22" name="Grace" city="Berlin" department="it" salary="90" />
		<i id="23" name="Henry" city="London" department="it" salary="104" />
		<i id="24" name="Irene" city="Berlin" department="it" salary="104" />
		<i id="25" name="Frank" city="Berlin" department="it" salary="120" />
		<i id="31" name="Cindy" city="Berlin" department="sales" salary="96" />
		<i id="32" name="Dave" city="London" department="sales" salary="96" />
		<i id="33" name="Alice" city="Berlin" department="sales" salary="100" />
	</Result>
</Data>